{"author": "Not Available", "source": "Scared_Text_Archive", "originalTitle": "Rig_Veda_Rv09108", "text": {"0": "for indra flow thou soma on as gladdening juice most sweet intelligent.", "1": "great cheering dwelling most in heaven.", "2": "thou of whom having drunk the steer acts like a steer drinking of this that finds the light.", "3": "he excellently wise is come to strengthening food to spoil and wealth like eta\u015ba.", "4": "for verily pavamana thou hast splendidest called all the generations of.", "5": "the gods to immortality.", "6": "by whom dadhyac navagva opens fastened doors by whom the sages gained their wish.", "7": "by whom they won the fame of lovely am\u1e5bta in the felicity of gods.", "8": "effused he floweth in a stream best rapturegiver in the long wool of the sheep.", "9": "sporting as \u0092twere the waters wave.", "10": "he who from out the rocky cavern took with might the redmrefulgent watery cows.", "11": "thou masterest the stable full of kine and steeds burst it brave lord like one in mail.", "12": "press ye and pour him like a steed laudworthy speeding through the region and the flood.", "13": "who swims in water roan in wood.", "14": "increaser of the water steer with thousand streams dear to the race of deities.", "15": "who born in law hath waxen mighty by the law king god and lofty ordinance.", "16": "make splendid glory shine on us thou lord of strengthening food god as the friend of gods.", "17": "unclose the fount of middle air.", "18": "roll onward to the bowls o mighty one effused as prince supporter of the tribes.", "19": "pour on us rain from heaven send us the waters flow incite our thoughts to win the spoil.", "20": "they have drained him the steer of heaven him with a thousand streams distilling rapturous joy.", "21": "him who brings all things excellent.", "22": "the mighty one was born immortal giving life lightening darkness with his shine.", "23": "wcllpraised by sages he hath by his wondrous power assumed the threefold as his robe.", "24": "effused is he who brings good things who brings us bounteous gifts and sweet refreshing food.", "25": "soma who brings us quiet homes.", "26": "he whom our indra and the marut host shall drink bhaga shall drink with aryarnan.", "27": "by whom we bring to us mitra and varu\u1e47a and indra for our great defence.", "28": "soma for indras drink do thou led by the men wellwcaponcd and most gladdening.", "29": "flow on with greatest store of sweets.", "30": "enter the somaholder even indras heart as rivers pass into the sea.", "31": "acceptable to mitra v\u0101yu varu\u1e47a the noblest pillar of the heavens."}, "sourceLink": "http://sacred-texts.com/hin/index.htm", "language": "English", "englishTitle": "Rig_Veda_Rv09108"}