{"author": "Not Available", "source": "Scared_Text_Archive", "originalTitle": "Rig_Veda_Rv08032", "text": {"0": "kanvas tell forth with song the deeds of indra the impetuous.", "1": "wrought in the somas wild delight.", "2": "strong god he slew anarsani srbinda pipru and the fiend.", "3": "ah\u012b\u015buva and loosed the floods.", "4": "thou broughtest down the dwellingplace the height of lofty arbuda.", "5": "that exploit indra must be famed.", "6": "bold to your famous soma i call the fairvisored god for aid.", "7": "down like a torrent from the hill.", "8": "rejoicing in the somadraughts hero burst open like a fort.", "9": "the stall of horses and of kine.", "10": "if my libation gladdens if thou takest pleasure in my laud.", "11": "come with thy godhead from afar.", "12": "o indra lover of the song the singers of thy praise are we.", "13": "o somadrinker quicken us.", "14": "and taking thy delight with us bring us still undiminished food.", "15": "great is thy wealth o maghavan.", "16": "make thou us rich in herds of kine in steeds in gold let us exert.", "17": "our strength in sacrificial gifts.", "18": "let us call him to aid whose hands stretch far to whom high laud is due.", "19": "who worketh well to succour us.", "20": "he \u015aatakratu even in fight acts as a v\u1e5btraslayer still.", "21": "he gives his worshippers much wealth.", "22": "may he this aakra strengthen us boon god who satisfies our needs.", "23": "indra with all lhis saving helps.", "24": "to him the mighty stream of wealth the somapressers rescuing friend.", "25": "to indra sing your song of praise.", "26": "who bringeth what is great and firm who winneth glory in his wars.", "27": "lord of vast wealth through power and might.", "28": "there liveth none to cheek or stay his energies and gracious deeds.", "29": "none who can say he giveth not.", "30": "no debt is due by brahmans now by active men who press the juice.", "31": "well hath each somadraught been paid.", "32": "sing ye to him who must be praised say lauds to him who must be praised.", "33": "bring prayer to him who must be praised.", "34": "may be unchecked strong meet for praise bring hundreds thousands forth to light.", "35": "indra who aids the worshipper.", "36": "go with thy godlike nature forth go where the folk are calling thee.", "37": "drink indra of the drops we pour.", "38": "drink milky draughts which are thine own this too which was with tugrya once.", "39": "this is it indra that is thine.", "40": "pass him who psours libations out in angry mood or after sin.", "41": "here drink the juice we offer thee.", "42": "over the three great distances past the five peoples go thy way.", "43": "o indra noticing our voice.", "44": "send forth thy ray like s\u016brya let my songs attract thee hitherward.", "45": "like waters gathering to the vale.", "46": "now to the hero fair of cheek adhvaryu pour the soma forth.", "47": "bring of the juice that he may drink.", "48": "who cleft the watercloud in twain loosed rivers for their downward flow.", "49": "and set the ripe milk in the kine.", "50": "he meet for praise slew v\u1e5btra slew ah\u012b\u015buva urnavabhas son.", "51": "and pierced through arbuda with frost.", "52": "to him your matchless mighty one unconquerable conqueror.", "53": "sing forth the prayer which gods have given.", "54": "indra who in the wild delight of soma juice considers here.", "55": "all holy laws among the gods.", "56": "hither let these thy bays who share thy banquet steeds with golden manes.", "57": "convey thee to the feast prepared.", "58": "hither o thou whom many laud the bays whom priyamedha praised.", "59": "shall bring thee to the somadraught."}, "sourceLink": "http://sacred-texts.com/hin/index.htm", "language": "English", "englishTitle": "Rig_Veda_Rv08032"}