{"author": "Not Available", "source": "Scared_Text_Archive", "originalTitle": "Rig_Veda_Rv09033", "text": {"0": "like waves of waters skilled in song the juices of the soma speed.", "1": "onward as buffaloes to woods.", "2": "with stream of sacrifice the brown bright drops have flowed with strength in store.", "3": "of kine into the wooden vats.", "4": "to indra v\u0101yu varu\u1e47a to vi\u1e63\u1e47u and the maruts flow.", "5": "the drops of soma juice effused.", "6": "three several words are uttered kine are owing cows who give their milk.", "7": "the tawnyhued goes bellowing on.", "8": "the young and sacred mothers of the holy rite have uttered praise.", "9": "they decorate the child of heaven.", "10": "from every side o soma for our profit pour thou forth four seas.", "11": "filled full of riches thousandfold."}, "sourceLink": "http://sacred-texts.com/hin/index.htm", "language": "English", "englishTitle": "Rig_Veda_Rv09033"}