{"author": "Not Available", "source": "Scared_Text_Archive", "originalTitle": "Rig_Veda_Rv01071", "text": {"0": "loving the loving one as wives their husband the sisters of one home have urged him forward.", "1": "brightcoloured even as the cows love morning dark breaking forth to view and redly beaming.", "2": "our sires with lauds burst e\u0092en the firmset fortress yea the a\u1e45girases with roar the mountain.", "3": "they made for us a way to reach high heaven they found us day light days sign beams of morning.", "4": "they stablished order made his service fruitful then parting them among the longing faithful.", "5": "not thirsting after aught they come most active while with sweet food the race of gods they strengthen.", "6": "since m\u0101tari\u015bvan fardiffused hath stirred him and he in every house grown bright and noble.", "7": "he bh\u1e5bgulike i hath gone as his companion as on commission to a greater sovran.", "8": "when man poured juice to heaven the mighty father he knew and freed himself from close embracement.", "9": "the archer boldly shot at him his arrow and the god threw his splendour on his daughter.", "10": "whoso hath flames for thee within his dwelling or brings the worship which thou lovest daily.", "11": "do thou of double might increase his substance may he whom thou incitest meet with riches.", "12": "all sacrificial viands wait on agni as the seven mighty rivers seek the ocean.", "13": "not by our brethren was our food discovered find with the gods care for us thou who knowest.", "14": "when light hath filled the lord of men for increase straight from the heaven descends the limpid moisture.", "15": "agni hath brought to light and filled with spirit the youthful host blameless and well providing.", "16": "he who like thought goes swiftly on his journey the sun alone is ever lord of riches.", "17": "the kings with fair hands varu\u1e47a and mitra protect the precious nectar in our cattle.", "18": "o agni break not our ancestral friendship sage as thou art endowed with deepest knowledge.", "19": "old age like gathering cloud impairs the body before that evil be come nigh protect me."}, "sourceLink": "http://sacred-texts.com/hin/index.htm", "language": "English", "englishTitle": "Rig_Veda_Rv01071"}